{
  "BusinessTypeID": 1,
  "BusinessTypeName": "CTCP Thường",
  "Company": "AAT",
  "Currency": "VND",
  "BaseCurrency": null,
  "CurrencyUnit": 1,
  "IncomeStatement": [
    {
      "Item": "Doanh thu bán hàng và cung cấp dịch vụ",
      "Values": {
        "KyNay": 583009927395,
        "KyTruoc": 599354540320,
        "LuyKe_KyNay": null,
        "LuyKe_KyTruoc": null
      },
      "ReportNormID": null,
      "Code": "01",
      "NormName": null,
      "PublishNormCode": null,
      "ParentName": null
    },
    {
      "Item": "Doanh thu thuần bán hàng và cung cấp dịch vụ",
      "Values": {
        "KyNay": 583009927395,
        "KyTruoc": 599354540320,
        "LuyKe_KyNay": null,
        "LuyKe_KyTruoc": null
      },
      "ReportNormID": null,
      "Code": "10",
      "NormName": null,
      "PublishNormCode": null,
      "ParentName": null
    },
    {
      "Item": "Giá vốn hàng bán",
      "Values": {
        "KyNay": 530233706850,
        "KyTruoc": 552233080356,
        "LuyKe_KyNay": null,
        "LuyKe_KyTruoc": null
      },
      "ReportNormID": null,
      "Code": "11",
      "NormName": null,
      "PublishNormCode": null,
      "ParentName": null
    },
    {
      "Item": "Lợi nhuận gộp về bán hàng và cung cấp dịch vụ",
      "Values": {
        "KyNay": 52776220546,
        "KyTruoc": 47121459964,
        "LuyKe_KyNay": null,
        "LuyKe_KyTruoc": null
      },
      "ReportNormID": null,
      "Code": "20",
      "NormName": null,
      "PublishNormCode": null,
      "ParentName": null
    },
    {
      "Item": "Doanh thu hoạt động tài chính",
      "Values": {
        "KyNay": 6690610681,
        "KyTruoc": 2498754473,
        "LuyKe_KyNay": null,
        "LuyKe_KyTruoc": null
      },
      "ReportNormID": null,
      "Code": "21",
      "NormName": null,
      "PublishNormCode": null,
      "ParentName": null
    },
    {
      "Item": "Chi phí tài chính",
      "Values": {
        "KyNay": 24526384148,
        "KyTruoc": 25588238928,
        "LuyKe_KyNay": null,
        "LuyKe_KyTruoc": null
      },
      "ReportNormID": null,
      "Code": "22",
      "NormName": null,
      "PublishNormCode": null,
      "ParentName": null
    },
    {
      "Item": "Chi phí lãi vay",
      "Values": {
        "KyNay": 20668976618,
        "KyTruoc": 23346940499,
        "LuyKe_KyNay": null,
        "LuyKe_KyTruoc": null
      },
      "ReportNormID": null,
      "Code": "23",
      "NormName": null,
      "PublishNormCode": null,
      "ParentName": "Chi phí tài chính"
    },
    {
      "Item": "Chi phí bán hàng",
      "Values": {
        "KyNay": 11292331741,
        "KyTruoc": 5839595312,
        "LuyKe_KyNay": null,
        "LuyKe_KyTruoc": null
      },
      "ReportNormID": null,
      "Code": "25",
      "NormName": null,
      "PublishNormCode": null,
      "ParentName": null
    },
    {
      "Item": "Chi phí quản lý doanh nghiệp",
      "Values": {
        "KyNay": 34406827154,
        "KyTruoc": 11683135646,
        "LuyKe_KyNay": null,
        "LuyKe_KyTruoc": null
      },
      "ReportNormID": null,
      "Code": "26",
      "NormName": null,
      "PublishNormCode": null,
      "ParentName": null
    },
    {
      "Item": "Lợi nhuận thuần từ hoạt động kinh doanh",
      "Values": {
        "KyNay": -10758711815,
        "KyTruoc": 6509244551,
        "LuyKe_KyNay": null,
        "LuyKe_KyTruoc": null
      },
      "ReportNormID": null,
      "Code": "30",
      "NormName": null,
      "PublishNormCode": null,
      "ParentName": null
    },
    {
      "Item": "Thu nhập khác",
      "Values": {
        "KyNay": 8621250214,
        "KyTruoc": 791982243,
        "LuyKe_KyNay": null,
        "LuyKe_KyTruoc": null
      },
      "ReportNormID": null,
      "Code": "31",
      "NormName": null,
      "PublishNormCode": null,
      "ParentName": null
    },
    {
      "Item": "Chi phí khác",
      "Values": {
        "KyNay": 2741639333,
        "KyTruoc": 7632188191,
        "LuyKe_KyNay": null,
        "LuyKe_KyTruoc": null
      },
      "ReportNormID": null,
      "Code": "32",
      "NormName": null,
      "PublishNormCode": null,
      "ParentName": null
    },
    {
      "Item": "Lợi nhuận khác",
      "Values": {
        "KyNay": 5879610882,
        "KyTruoc": -6840205948,
        "LuyKe_KyNay": null,
        "LuyKe_KyTruoc": null
      },
      "ReportNormID": null,
      "Code": "40",
      "NormName": null,
      "PublishNormCode": null,
      "ParentName": null
    },
    {
      "Item": "Tổng lợi nhuận kế toán trước thuế",
      "Values": {
        "KyNay": -4879100934,
        "KyTruoc": -330961397,
        "LuyKe_KyNay": null,
        "LuyKe_KyTruoc": null
      },
      "ReportNormID": null,
      "Code": "50",
      "NormName": null,
      "PublishNormCode": null,
      "ParentName": null
    },
    {
      "Item": "Chi phí thuế TNDN hiện hành",
      "Values": {
        "KyNay": 3427537230,
        "KyTruoc": 2135614902,
        "LuyKe_KyNay": null,
        "LuyKe_KyTruoc": null
      },
      "ReportNormID": null,
      "Code": "51",
      "NormName": null,
      "PublishNormCode": null,
      "ParentName": null
    },
    {
      "Item": "Chi phí thuế TNDN hoãn lại",
      "Values": {
        "KyNay": 4443149,
        "KyTruoc": null,
        "LuyKe_KyNay": null,
        "LuyKe_KyTruoc": null
      },
      "ReportNormID": null,
      "Code": "52",
      "NormName": null,
      "PublishNormCode": null,
      "ParentName": null
    },
    {
      "Item": "Lợi nhuận sau thuế thu nhập doanh nghiệp",
      "Values": {
        "KyNay": -8311081313,
        "KyTruoc": -2466576299,
        "LuyKe_KyNay": null,
        "LuyKe_KyTruoc": null
      },
      "ReportNormID": null,
      "Code": "60",
      "NormName": null,
      "PublishNormCode": null,
      "ParentName": null
    },
    {
      "Item": "Lợi nhuận sau thuế của Công ty Mẹ",
      "Values": {
        "KyNay": -8345961789,
        "KyTruoc": -2466576299,
        "LuyKe_KyNay": null,
        "LuyKe_KyTruoc": null
      },
      "ReportNormID": null,
      "Code": "61",
      "NormName": null,
      "PublishNormCode": null,
      "ParentName": "Lợi nhuận sau thuế thu nhập doanh nghiệp"
    },
    {
      "Item": "Lợi nhuận sau thuế của cổ đông không kiểm soát",
      "Values": {
        "KyNay": 34880476,
        "KyTruoc": null,
        "LuyKe_KyNay": null,
        "LuyKe_KyTruoc": null
      },
      "ReportNormID": null,
      "Code": "62",
      "NormName": null,
      "PublishNormCode": null,
      "ParentName": "Lợi nhuận sau thuế thu nhập doanh nghiệp"
    },
    {
      "Item": "Lãi cơ bản trên cổ phiếu",
      "Values": {
        "KyNay": -118,
        "KyTruoc": -35,
        "LuyKe_KyNay": null,
        "LuyKe_KyTruoc": null
      },
      "ReportNormID": null,
      "Code": "70",
      "NormName": null,
      "PublishNormCode": null,
      "ParentName": null
    },
    {
      "Item": "Lãi suy giảm trên cổ phiếu",
      "Values": {
        "KyNay": -118,
        "KyTruoc": -35,
        "LuyKe_KyNay": null,
        "LuyKe_KyTruoc": null
      },
      "ReportNormID": null,
      "Code": "71",
      "NormName": null,
      "PublishNormCode": null,
      "ParentName": null
    }
  ],
  "BalanceSheet": [
    {
      "Item": "TỔNG CỘNG TÀI SẢN",
      "Values": {
        "KyNay": 1334267673045,
        "KyTruoc": 1011341063201,
        "LuyKe_KyNay": null,
        "LuyKe_KyTruoc": null
      },
      "ReportNormID": null,
      "Code": "270",
      "NormName": null,
      "PublishNormCode": null,
      "ParentName": null
    },
    {
      "Item": "TÀI SẢN",
      "Values": {
        "KyNay": null,
        "KyTruoc": null,
        "LuyKe_KyNay": null,
        "LuyKe_KyTruoc": null
      },
      "ReportNormID": null,
      "Code": null,
      "NormName": null,
      "PublishNormCode": null,
      "ParentName": null
    },
    {
      "Item": "TÀI SẢN NGẮN HẠN",
      "Values": {
        "KyNay": 338201142715,
        "KyTruoc": 468060301717,
        "LuyKe_KyNay": null,
        "LuyKe_KyTruoc": null
      },
      "ReportNormID": null,
      "Code": null,
      "NormName": null,
      "PublishNormCode": null,
      "ParentName": "TÀI SẢN"
    },
    {
      "Item": "Tiền và các khoản tương đương tiền",
      "Values": {
        "KyNay": 11510430120,
        "KyTruoc": 2079219084,
        "LuyKe_KyNay": null,
        "LuyKe_KyTruoc": null
      },
      "ReportNormID": null,
      "Code": "110",
      "NormName": null,
      "PublishNormCode": null,
      "ParentName": "TÀI SẢN NGẮN HẠN"
    },
    {
      "Item": "Tiền",
      "Values": {
        "KyNay": 11510430120,
        "KyTruoc": 2079219084,
        "LuyKe_KyNay": null,
        "LuyKe_KyTruoc": null
      },
      "ReportNormID": null,
      "Code": "111",
      "NormName": null,
      "PublishNormCode": null,
      "ParentName": "Tiền và các khoản tương đương tiền"
    },
    {
      "Item": "Đầu tư tài chính ngắn hạn",
      "Values": {
        "KyNay": 26588010013,
        "KyTruoc": 20000000000,
        "LuyKe_KyNay": null,
        "LuyKe_KyTruoc": null
      },
      "ReportNormID": null,
      "Code": "120",
      "NormName": null,
      "PublishNormCode": null,
      "ParentName": "TÀI SẢN NGẮN HẠN"
    },
    {
      "Item": "Đầu tư nắm giữ đến ngày đáo hạn",
      "Values": {
        "KyNay": 26588010013,
        "KyTruoc": 20000000000,
        "LuyKe_KyNay": null,
        "LuyKe_KyTruoc": null
      },
      "ReportNormID": null,
      "Code": "123",
      "NormName": null,
      "PublishNormCode": null,
      "ParentName": "Đầu tư tài chính ngắn hạn"
    },
    {
      "Item": "Các khoản phải thu ngắn hạn",
      "Values": {
        "KyNay": 278576713658,
        "KyTruoc": 417455201374,
        "LuyKe_KyNay": null,
        "LuyKe_KyTruoc": null
      },
      "ReportNormID": null,
      "Code": "130",
      "NormName": null,
      "PublishNormCode": null,
      "ParentName": "TÀI SẢN NGẮN HẠN"
    },
    {
      "Item": "Phải thu ngắn hạn của khách hàng",
      "Values": {
        "KyNay": 40358004074,
        "KyTruoc": 54306382676,
        "LuyKe_KyNay": null,
        "LuyKe_KyTruoc": null
      },
      "ReportNormID": null,
      "Code": "131",
      "NormName": null,
      "PublishNormCode": null,
      "ParentName": "Các khoản phải thu ngắn hạn"
    },
    {
      "Item": "Trả trước cho người bán ngắn hạn",
      "Values": {
        "KyNay": 165322200642,
        "KyTruoc": 113940196982,
        "LuyKe_KyNay": null,
        "LuyKe_KyTruoc": null
      },
      "ReportNormID": null,
      "Code": "132",
      "NormName": null,
      "PublishNormCode": null,
      "ParentName": "Các khoản phải thu ngắn hạn"
    },
    {
      "Item": "Phải thu về cho vay ngắn hạn",
      "Values": {
        "KyNay": 2844300001,
        "KyTruoc": 55900000000,
        "LuyKe_KyNay": null,
        "LuyKe_KyTruoc": null
      },
      "ReportNormID": null,
      "Code": "135",
      "NormName": null,
      "PublishNormCode": null,
      "ParentName": "Các khoản phải thu ngắn hạn"
    },
    {
      "Item": "Phải thu ngắn hạn khác",
      "Values": {
        "KyNay": 92530514835,
        "KyTruoc": 195218324183,
        "LuyKe_KyNay": null,
        "LuyKe_KyTruoc": null
      },
      "ReportNormID": null,
      "Code": "136",
      "NormName": null,
      "PublishNormCode": null,
      "ParentName": "Các khoản phải thu ngắn hạn"
    },
    {
      "Item": "Dự phòng các khoản phải thu khó đòi",
      "Values": {
        "KyNay": -22478305894,
        "KyTruoc": -1909702467,
        "LuyKe_KyNay": null,
        "LuyKe_KyTruoc": null
      },
      "ReportNormID": null,
      "Code": "137",
      "NormName": null,
      "PublishNormCode": null,
      "ParentName": "Các khoản phải thu ngắn hạn"
    },
    {
      "Item": "Hàng tồn kho",
      "Values": {
        "KyNay": 13269530449,
        "KyTruoc": 27578288832,
        "LuyKe_KyNay": null,
        "LuyKe_KyTruoc": null
      },
      "ReportNormID": null,
      "Code": "140",
      "NormName": null,
      "PublishNormCode": null,
      "ParentName": "TÀI SẢN NGẮN HẠN"
    },
    {
      "Item": "Hàng tồn kho",
      "Values": {
        "KyNay": 17266781943,
        "KyTruoc": 29789466569,
        "LuyKe_KyNay": null,
        "LuyKe_KyTruoc": null
      },
      "ReportNormID": null,
      "Code": "141",
      "NormName": null,
      "PublishNormCode": null,
      "ParentName": "Hàng tồn kho"
    },
    {
      "Item": "Dự phòng giảm giá hàng tồn kho",
      "Values": {
        "KyNay": -3997251494,
        "KyTruoc": -2211177737,
        "LuyKe_KyNay": null,
        "LuyKe_KyTruoc": null
      },
      "ReportNormID": null,
      "Code": "149",
      "NormName": null,
      "PublishNormCode": null,
      "ParentName": "Hàng tồn kho"
    },
    {
      "Item": "Tài sản ngắn hạn khác",
      "Values": {
        "KyNay": 8256458475,
        "KyTruoc": 947592427,
        "LuyKe_KyNay": null,
        "LuyKe_KyTruoc": null
      },
      "ReportNormID": null,
      "Code": "150",
      "NormName": null,
      "PublishNormCode": null,
      "ParentName": "TÀI SẢN NGẮN HẠN"
    },
    {
      "Item": "Thuế GTGT được khấu trừ",
      "Values": {
        "KyNay": 8133399516,
        "KyTruoc": 824533468,
        "LuyKe_KyNay": null,
        "LuyKe_KyTruoc": null
      },
      "ReportNormID": null,
      "Code": "152",
      "NormName": null,
      "PublishNormCode": null,
      "ParentName": "Tài sản ngắn hạn khác"
    },
    {
      "Item": "Thuế và các khoản khác phải thu Nhà nước",
      "Values": {
        "KyNay": 123058959,
        "KyTruoc": 123058959,
        "LuyKe_KyNay": null,
        "LuyKe_KyTruoc": null
      },
      "ReportNormID": null,
      "Code": "153",
      "NormName": null,
      "PublishNormCode": null,
      "ParentName": "Tài sản ngắn hạn khác"
    },
    {
      "Item": "TÀI SẢN DÀI HẠN",
      "Values": {
        "KyNay": 996066530330,
        "KyTruoc": 543280761484,
        "LuyKe_KyNay": null,
        "LuyKe_KyTruoc": null
      },
      "ReportNormID": null,
      "Code": "200",
      "NormName": null,
      "PublishNormCode": null,
      "ParentName": "TÀI SẢN"
    },
    {
      "Item": "Các khoản phải thu dài hạn",
      "Values": {
        "KyNay": 97154164742,
        "KyTruoc": 31444164742,
        "LuyKe_KyNay": null,
        "LuyKe_KyTruoc": null
      },
      "ReportNormID": null,
      "Code": "210",
      "NormName": null,
      "PublishNormCode": null,
      "ParentName": "TÀI SẢN DÀI HẠN"
    },
    {
      "Item": "Phải thu về cho vay dài hạn",
      "Values": {
        "KyNay": 95000000000,
        "KyTruoc": null,
        "LuyKe_KyNay": null,
        "LuyKe_KyTruoc": null
      },
      "ReportNormID": null,
      "Code": "215",
      "NormName": null,
      "PublishNormCode": null,
      "ParentName": "Các khoản phải thu dài hạn"
    },
    {
      "Item": "Phải thu dài hạn khác",
      "Values": {
        "KyNay": 2154164742,
        "KyTruoc": 31444164742,
        "LuyKe_KyNay": null,
        "LuyKe_KyTruoc": null
      },
      "ReportNormID": null,
      "Code": "216",
      "NormName": null,
      "PublishNormCode": null,
      "ParentName": "Các khoản phải thu dài hạn"
    },
    {
      "Item": "Tài sản cố định",
      "Values": {
        "KyNay": 78822927681,
        "KyTruoc": 136188628937,
        "LuyKe_KyNay": null,
        "LuyKe_KyTruoc": null
      },
      "ReportNormID": null,
      "Code": "220",
      "NormName": null,
      "PublishNormCode": null,
      "ParentName": "TÀI SẢN DÀI HẠN"
    },
    {
      "Item": "Tài sản cố định hữu hình",
      "Values": {
        "KyNay": 75334526298,
        "KyTruoc": 125159925620,
        "LuyKe_KyNay": null,
        "LuyKe_KyTruoc": null
      },
      "ReportNormID": null,
      "Code": "221",
      "NormName": null,
      "PublishNormCode": null,
      "ParentName": "Tài sản cố định"
    },
    {
      "Item": "- Nguyên giá",
      "Values": {
        "KyNay": 170144003095,
        "KyTruoc": 299634188603,
        "LuyKe_KyNay": null,
        "LuyKe_KyTruoc": null
      },
      "ReportNormID": null,
      "Code": "222",
      "NormName": null,
      "PublishNormCode": null,
      "ParentName": "Tài sản cố định hữu hình"
    },
    {
      "Item": "- Giá trị hao mòn luỹ kế",
      "Values": {
        "KyNay": -94809476797,
        "KyTruoc": -174474262983,
        "LuyKe_KyNay": null,
        "LuyKe_KyTruoc": null
      },
      "ReportNormID": null,
      "Code": "223",
      "NormName": null,
      "PublishNormCode": null,
      "ParentName": "Tài sản cố định hữu hình"
    },
    {
      "Item": "Tài sản cố định thuê tài chính",
      "Values": {
        "KyNay": 3488401383,
        "KyTruoc": 5122788183,
        "LuyKe_KyNay": null,
        "LuyKe_KyTruoc": null
      },
      "ReportNormID": null,
      "Code": "224",
      "NormName": null,
      "PublishNormCode": null,
      "ParentName": "Tài sản cố định"
    },
    {
      "Item": "- Nguyên giá",
      "Values": {
        "KyNay": 6257540771,
        "KyTruoc": 6257540771,
        "LuyKe_KyNay": null,
        "LuyKe_KyTruoc": null
      },
      "ReportNormID": null,
      "Code": "225",
      "NormName": null,
      "PublishNormCode": null,
      "ParentName": "Tài sản cố định thuê tài chính"
    },
    {
      "Item": "- Giá trị hao mòn luỹ kế",
      "Values": {
        "KyNay": -2769139388,
        "KyTruoc": -1134752588,
        "LuyKe_KyNay": null,
        "LuyKe_KyTruoc": null
      },
      "ReportNormID": null,
      "Code": "226",
      "NormName": null,
      "PublishNormCode": null,
      "ParentName": "Tài sản cố định thuê tài chính"
    },
    {
      "Item": "Tài sản cố định vô hình",
      "Values": {
        "KyNay": null,
        "KyTruoc": 5905915134,
        "LuyKe_KyNay": null,
        "LuyKe_KyTruoc": null
      },
      "ReportNormID": null,
      "Code": "227",
      "NormName": null,
      "PublishNormCode": null,
      "ParentName": "Tài sản cố định"
    },
    {
      "Item": "- Nguyên giá",
      "Values": {
        "KyNay": null,
        "KyTruoc": 6513877000,
        "LuyKe_KyNay": null,
        "LuyKe_KyTruoc": null
      },
      "ReportNormID": null,
      "Code": "228",
      "NormName": null,
      "PublishNormCode": null,
      "ParentName": "Tài sản cố định vô hình"
    },
    {
      "Item": "- Giá trị hao mòn luỹ kế",
      "Values": {
        "KyNay": null,
        "KyTruoc": -607961866,
        "LuyKe_KyNay": null,
        "LuyKe_KyTruoc": null
      },
      "ReportNormID": null,
      "Code": "229",
      "NormName": null,
      "PublishNormCode": null,
      "ParentName": "Tài sản cố định vô hình"
    },
    {
      "Item": "Bất động sản đầu tư",
      "Values": {
        "KyNay": 510842724420,
        "KyTruoc": 294346753470,
        "LuyKe_KyNay": null,
        "LuyKe_KyTruoc": null
      },
      "ReportNormID": null,
      "Code": "230",
      "NormName": null,
      "PublishNormCode": null,
      "ParentName": "TÀI SẢN DÀI HẠN"
    },
    {
      "Item": "- Nguyên giá",
      "Values": {
        "KyNay": 674291077766,
        "KyTruoc": 388176371727,
        "LuyKe_KyNay": null,
        "LuyKe_KyTruoc": null
      },
      "ReportNormID": null,
      "Code": "231",
      "NormName": null,
      "PublishNormCode": null,
      "ParentName": "Bất động sản đầu tư"
    },
    {
      "Item": "- Giá trị hao mòn luỹ kế",
      "Values": {
        "KyNay": -163448353346,
        "KyTruoc": -93829618257,
        "LuyKe_KyNay": null,
        "LuyKe_KyTruoc": null
      },
      "ReportNormID": null,
      "Code": "232",
      "NormName": null,
      "PublishNormCode": null,
      "ParentName": "Bất động sản đầu tư"
    },
    {
      "Item": "Tài sản dở dang dài hạn",
      "Values": {
        "KyNay": 166738988321,
        "KyTruoc": 810673000,
        "LuyKe_KyNay": null,
        "LuyKe_KyTruoc": null
      },
      "ReportNormID": null,
      "Code": "240",
      "NormName": null,
      "PublishNormCode": null,
      "ParentName": "TÀI SẢN DÀI HẠN"
    },
    {
      "Item": "Chi phí xây dựng cơ bản dở dang",
      "Values": {
        "KyNay": 166738988321,
        "KyTruoc": 810673000,
        "LuyKe_KyNay": null,
        "LuyKe_KyTruoc": null
      },
      "ReportNormID": null,
      "Code": "242",
      "NormName": null,
      "PublishNormCode": null,
      "ParentName": "Tài sản dở dang dài hạn"
    },
    {
      "Item": "Đầu tư tài chính dài hạn",
      "Values": {
        "KyNay": null,
        "KyTruoc": 67322000000,
        "LuyKe_KyNay": null,
        "LuyKe_KyTruoc": null
      },
      "ReportNormID": null,
      "Code": "250",
      "NormName": null,
      "PublishNormCode": null,
      "ParentName": "TÀI SẢN DÀI HẠN"
    },
    {
      "Item": "Đầu tư vào công ty liên doanh, liên kết",
      "Values": {
        "KyNay": null,
        "KyTruoc": 67322000000,
        "LuyKe_KyNay": null,
        "LuyKe_KyTruoc": null
      },
      "ReportNormID": null,
      "Code": "252",
      "NormName": null,
      "PublishNormCode": null,
      "ParentName": "Đầu tư tài chính dài hạn"
    },
    {
      "Item": "Tài sản dài hạn khác",
      "Values": {
        "KyNay": 142507725166,
        "KyTruoc": 13168541335,
        "LuyKe_KyNay": null,
        "LuyKe_KyTruoc": null
      },
      "ReportNormID": null,
      "Code": "260",
      "NormName": null,
      "PublishNormCode": null,
      "ParentName": "TÀI SẢN DÀI HẠN"
    },
    {
      "Item": "Chi phí trả trước dài hạn",
      "Values": {
        "KyNay": 66839359666,
        "KyTruoc": 13168541335,
        "LuyKe_KyNay": null,
        "LuyKe_KyTruoc": null
      },
      "ReportNormID": null,
      "Code": "261",
      "NormName": null,
      "PublishNormCode": null,
      "ParentName": "Tài sản dài hạn khác"
    },
    {
      "Item": "Lợi thế thương mại",
      "Values": {
        "KyNay": 75668365500,
        "KyTruoc": null,
        "LuyKe_KyNay": null,
        "LuyKe_KyTruoc": null
      },
      "ReportNormID": null,
      "Code": "269",
      "NormName": null,
      "PublishNormCode": null,
      "ParentName": "Tài sản dài hạn khác"
    },
    {
      "Item": "NGUỒN VỐN",
      "Values": {
        "KyNay": null,
        "KyTruoc": null,
        "LuyKe_KyNay": null,
        "LuyKe_KyTruoc": null
      },
      "ReportNormID": null,
      "Code": null,
      "NormName": null,
      "PublishNormCode": null,
      "ParentName": null
    },
    {
      "Item": "NỢ PHẢI TRẢ",
      "Values": {
        "KyNay": 608875691459,
        "KyTruoc": 303719940136,
        "LuyKe_KyNay": null,
        "LuyKe_KyTruoc": null
      },
      "ReportNormID": null,
      "Code": "300",
      "NormName": null,
      "PublishNormCode": null,
      "ParentName": "NGUỒN VỐN"
    },
    {
      "Item": "Nợ ngắn hạn",
      "Values": {
        "KyNay": 200201307045,
        "KyTruoc": 180696832053,
        "LuyKe_KyNay": null,
        "LuyKe_KyTruoc": null
      },
      "ReportNormID": null,
      "Code": "310",
      "NormName": null,
      "PublishNormCode": null,
      "ParentName": "NỢ PHẢI TRẢ"
    },
    {
      "Item": "Phải trả người bán ngắn hạn",
      "Values": {
        "KyNay": 21369085170,
        "KyTruoc": 31694531405,
        "LuyKe_KyNay": null,
        "LuyKe_KyTruoc": null
      },
      "ReportNormID": null,
      "Code": "311",
      "NormName": null,
      "PublishNormCode": null,
      "ParentName": "Nợ ngắn hạn"
    },
    {
      "Item": "Người mua trả tiền trước ngắn hạn",
      "Values": {
        "KyNay": 210124213,
        "KyTruoc": 210000000,
        "LuyKe_KyNay": null,
        "LuyKe_KyTruoc": null
      },
      "ReportNormID": null,
      "Code": "312",
      "NormName": null,
      "PublishNormCode": null,
      "ParentName": "Nợ ngắn hạn"
    },
    {
      "Item": "Thuế và các khoản phải nộp Nhà nước",
      "Values": {
        "KyNay": 14090410982,
        "KyTruoc": 6220067698,
        "LuyKe_KyNay": null,
        "LuyKe_KyTruoc": null
      },
      "ReportNormID": null,
      "Code": "313",
      "NormName": null,
      "PublishNormCode": null,
      "ParentName": "Nợ ngắn hạn"
    },
    {
      "Item": "Phải trả người lao động",
      "Values": {
        "KyNay": 5577880809,
        "KyTruoc": 4563695000,
        "LuyKe_KyNay": null,
        "LuyKe_KyTruoc": null
      },
      "ReportNormID": null,
      "Code": "314",
      "NormName": null,
      "PublishNormCode": null,
      "ParentName": "Nợ ngắn hạn"
    },
    {
      "Item": "Chi phí phải trả ngắn hạn",
      "Values": {
        "KyNay": 1068303041,
        "KyTruoc": null,
        "LuyKe_KyNay": null,
        "LuyKe_KyTruoc": null
      },
      "ReportNormID": null,
      "Code": "315",
      "NormName": null,
      "PublishNormCode": null,
      "ParentName": "Nợ ngắn hạn"
    },
    {
      "Item": "Doanh thu chưa thực hiện ngắn hạn",
      "Values": {
        "KyNay": 21754733156,
        "KyTruoc": null,
        "LuyKe_KyNay": null,
        "LuyKe_KyTruoc": null
      },
      "ReportNormID": null,
      "Code": "318",
      "NormName": null,
      "PublishNormCode": null,
      "ParentName": "Nợ ngắn hạn"
    },
    {
      "Item": "Phải trả ngắn hạn khác",
      "Values": {
        "KyNay": 1099018842,
        "KyTruoc": 443074082,
        "LuyKe_KyNay": null,
        "LuyKe_KyTruoc": null
      },
      "ReportNormID": null,
      "Code": "319",
      "NormName": null,
      "PublishNormCode": null,
      "ParentName": "Nợ ngắn hạn"
    },
    {
      "Item": "Vay và nợ thuê tài chính ngắn hạn",
      "Values": {
        "KyNay": 134930658002,
        "KyTruoc": 137464371038,
        "LuyKe_KyNay": null,
        "LuyKe_KyTruoc": null
      },
      "ReportNormID": null,
      "Code": "320",
      "NormName": null,
      "PublishNormCode": null,
      "ParentName": "Nợ ngắn hạn"
    },
    {
      "Item": "Quỹ khen thưởng, phúc lợi",
      "Values": {
        "KyNay": 101092830,
        "KyTruoc": 101092830,
        "LuyKe_KyNay": null,
        "LuyKe_KyTruoc": null
      },
      "ReportNormID": null,
      "Code": "322",
      "NormName": null,
      "PublishNormCode": null,
      "ParentName": "Nợ ngắn hạn"
    },
    {
      "Item": "Nợ dài hạn",
      "Values": {
        "KyNay": 408674384414,
        "KyTruoc": 123023108083,
        "LuyKe_KyNay": null,
        "LuyKe_KyTruoc": null
      },
      "ReportNormID": null,
      "Code": "330",
      "NormName": null,
      "PublishNormCode": null,
      "ParentName": "NỢ PHẢI TRẢ"
    },
    {
      "Item": "Chi phí phải trả dài hạn",
      "Values": {
        "KyNay": 76731385907,
        "KyTruoc": null,
        "LuyKe_KyNay": null,
        "LuyKe_KyTruoc": null
      },
      "ReportNormID": null,
      "Code": "333",
      "NormName": null,
      "PublishNormCode": null,
      "ParentName": "Nợ dài hạn"
    },
    {
      "Item": "Phải trả dài hạn khác",
      "Values": {
        "KyNay": 86279914540,
        "KyTruoc": 47252675709,
        "LuyKe_KyNay": null,
        "LuyKe_KyTruoc": null
      },
      "ReportNormID": null,
      "Code": "337",
      "NormName": null,
      "PublishNormCode": null,
      "ParentName": "Nợ dài hạn"
    },
    {
      "Item": "Vay và nợ thuê tài chính dài hạn",
      "Values": {
        "KyNay": 232880892368,
        "KyTruoc": 75770432374,
        "LuyKe_KyNay": null,
        "LuyKe_KyTruoc": null
      },
      "ReportNormID": null,
      "Code": "338",
      "NormName": null,
      "PublishNormCode": null,
      "ParentName": "Nợ dài hạn"
    },
    {
      "Item": "Thuế thu nhập hoãn lại phải trả",
      "Values": {
        "KyNay": 12782191599,
        "KyTruoc": null,
        "LuyKe_KyNay": null,
        "LuyKe_KyTruoc": null
      },
      "ReportNormID": null,
      "Code": "341",
      "NormName": null,
      "PublishNormCode": null,
      "ParentName": "Nợ dài hạn"
    },
    {
      "Item": "VỐN CHỦ SỞ HỮU",
      "Values": {
        "KyNay": 725391981586,
        "KyTruoc": 707621123065,
        "LuyKe_KyNay": null,
        "LuyKe_KyTruoc": null
      },
      "ReportNormID": null,
      "Code": "400",
      "NormName": null,
      "PublishNormCode": null,
      "ParentName": "NGUỒN VỐN"
    },
    {
      "Item": "Vốn chủ sở hữu",
      "Values": {
        "KyNay": 725391981586,
        "KyTruoc": 707621123065,
        "LuyKe_KyNay": null,
        "LuyKe_KyTruoc": null
      },
      "ReportNormID": null,
      "Code": "410",
      "NormName": null,
      "PublishNormCode": null,
      "ParentName": "VỐN CHỦ SỞ HỮU"
    },
    {
      "Item": "Vốn góp của chủ sở hữu",
      "Values": {
        "KyNay": 708191030000,
        "KyTruoc": 708191030000,
        "LuyKe_KyNay": null,
        "LuyKe_KyTruoc": null
      },
      "ReportNormID": null,
      "Code": "411",
      "NormName": null,
      "PublishNormCode": null,
      "ParentName": "Vốn chủ sở hữu"
    },
    {
      "Item": "- Cổ phiếu phổ thông có quyền biểu quyết",
      "Values": {
        "KyNay": 708191030000,
        "KyTruoc": 708191030000,
        "LuyKe_KyNay": null,
        "LuyKe_KyTruoc": null
      },
      "ReportNormID": null,
      "Code": "411a",
      "NormName": null,
      "PublishNormCode": null,
      "ParentName": "Vốn góp của chủ sở hữu"
    },
    {
      "Item": "Thặng dư vốn cổ phần",
      "Values": {
        "KyNay": -210000000,
        "KyTruoc": -210000000,
        "LuyKe_KyNay": null,
        "LuyKe_KyTruoc": null
      },
      "ReportNormID": null,
      "Code": "412",
      "NormName": null,
      "PublishNormCode": null,
      "ParentName": "Vốn chủ sở hữu"
    },
    {
      "Item": "Quỹ đầu tư phát triển",
      "Values": {
        "KyNay": 439500000,
        "KyTruoc": 439500000,
        "LuyKe_KyNay": null,
        "LuyKe_KyTruoc": null
      },
      "ReportNormID": null,
      "Code": "418",
      "NormName": null,
      "PublishNormCode": null,
      "ParentName": "Vốn chủ sở hữu"
    },
    {
      "Item": "Quỹ khác thuộc vốn chủ sở hữu",
      "Values": {
        "KyNay": 18000000,
        "KyTruoc": 18000000,
        "LuyKe_KyNay": null,
        "LuyKe_KyTruoc": null
      },
      "ReportNormID": null,
      "Code": "420",
      "NormName": null,
      "PublishNormCode": null,
      "ParentName": "Vốn chủ sở hữu"
    },
    {
      "Item": "Lợi nhuận sau thuế chưa phân phối",
      "Values": {
        "KyNay": -7322332187,
        "KyTruoc": -817406935,
        "LuyKe_KyNay": null,
        "LuyKe_KyTruoc": null
      },
      "ReportNormID": null,
      "Code": "421",
      "NormName": null,
      "PublishNormCode": null,
      "ParentName": "Vốn chủ sở hữu"
    },
    {
      "Item": "- LNST chưa phân phối lũy kế đến cuối năm trước",
      "Values": {
        "KyNay": -817406935,
        "KyTruoc": 1649169364,
        "LuyKe_KyNay": null,
        "LuyKe_KyTruoc": null
      },
      "ReportNormID": null,
      "Code": "421a",
      "NormName": null,
      "PublishNormCode": null,
      "ParentName": "Lợi nhuận sau thuế chưa phân phối"
    },
    {
      "Item": "- LNST chưa phân phối năm nay",
      "Values": {
        "KyNay": -6504925252,
        "KyTruoc": -2466576299,
        "LuyKe_KyNay": null,
        "LuyKe_KyTruoc": null
      },
      "ReportNormID": null,
      "Code": "421b",
      "NormName": null,
      "PublishNormCode": null,
      "ParentName": "Lợi nhuận sau thuế chưa phân phối"
    },
    {
      "Item": "Lợi ích cổ đông không kiểm soát",
      "Values": {
        "KyNay": 24275783773,
        "KyTruoc": null,
        "LuyKe_KyNay": null,
        "LuyKe_KyTruoc": null
      },
      "ReportNormID": null,
      "Code": "429",
      "NormName": null,
      "PublishNormCode": null,
      "ParentName": "Vốn chủ sở hữu"
    },
    {
      "Item": "TỔNG CỘNG NGUỒN VỐN",
      "Values": {
        "KyNay": 1334267673045,
        "KyTruoc": 1011341063201,
        "LuyKe_KyNay": null,
        "LuyKe_KyTruoc": null
      },
      "ReportNormID": null,
      "Code": "440",
      "NormName": null,
      "PublishNormCode": null,
      "ParentName": null
    }
  ],
  "CashFlow": [
    {
      "Item": "Lợi nhuận trước thuế",
      "Values": {
        "KyNay": -4879100934,
        "KyTruoc": -330961397,
        "LuyKe_KyNay": null,
        "LuyKe_KyTruoc": null
      },
      "ReportNormID": null,
      "Code": "01",
      "NormName": null,
      "PublishNormCode": null,
      "ParentName": null
    },
    {
      "Item": "Điều chỉnh cho các khoản",
      "Values": {
        "KyNay": null,
        "KyTruoc": null,
        "LuyKe_KyNay": null,
        "LuyKe_KyTruoc": null
      },
      "ReportNormID": null,
      "Code": null,
      "NormName": null,
      "PublishNormCode": null,
      "ParentName": null
    },
    {
      "Item": "Khấu hao TSCĐ và BĐSĐT",
      "Values": {
        "KyNay": 57882333736,
        "KyTruoc": 42969038194,
        "LuyKe_KyNay": null,
        "LuyKe_KyTruoc": null
      },
      "ReportNormID": null,
      "Code": "02",
      "NormName": null,
      "PublishNormCode": null,
      "ParentName": "Điều chỉnh cho các khoản"
    },
    {
      "Item": "Các khoản dự phòng",
      "Values": {
        "KyNay": 22354677184,
        "KyTruoc": 659446150,
        "LuyKe_KyNay": null,
        "LuyKe_KyTruoc": null
      },
      "ReportNormID": null,
      "Code": "03",
      "NormName": null,
      "PublishNormCode": null,
      "ParentName": "Điều chỉnh cho các khoản"
    },
    {
      "Item": "(Lãi)/lỗ các khoản chênh lệch tỷ giá hối đoái do đánh giá lại các khoản mục tiền tệ có gốc ngoại tệ",
      "Values": {
        "KyNay": 2675712566,
        "KyTruoc": 160236416,
        "LuyKe_KyNay": null,
        "LuyKe_KyTruoc": null
      },
      "ReportNormID": null,
      "Code": "04",
      "NormName": null,
      "PublishNormCode": null,
      "ParentName": "Điều chỉnh cho các khoản"
    },
    {
      "Item": "(Lãi)/lỗ hoạt động đầu tư",
      "Values": {
        "KyNay": -6911183366,
        "KyTruoc": -2301823358,
        "LuyKe_KyNay": null,
        "LuyKe_KyTruoc": null
      },
      "ReportNormID": null,
      "Code": "05",
      "NormName": null,
      "PublishNormCode": null,
      "ParentName": "Điều chỉnh cho các khoản"
    },
    {
      "Item": "Chi phí lãi vay",
      "Values": {
        "KyNay": 20668976618,
        "KyTruoc": 23182790632,
        "LuyKe_KyNay": null,
        "LuyKe_KyTruoc": null
      },
      "ReportNormID": null,
      "Code": "06",
      "NormName": null,
      "PublishNormCode": null,
      "ParentName": "Điều chỉnh cho các khoản"
    },
    {
      "Item": "Lợi nhuận từ hoạt động kinh doanh trước thay đổi vốn lưu động",
      "Values": {
        "KyNay": 91791415804,
        "KyTruoc": 64338726637,
        "LuyKe_KyNay": null,
        "LuyKe_KyTruoc": null
      },
      "ReportNormID": null,
      "Code": "08",
      "NormName": null,
      "PublishNormCode": null,
      "ParentName": null
    },
    {
      "Item": "(Tăng)/giảm các khoản phải thu",
      "Values": {
        "KyNay": 191934187715,
        "KyTruoc": 36375891607,
        "LuyKe_KyNay": null,
        "LuyKe_KyTruoc": null
      },
      "ReportNormID": null,
      "Code": "09",
      "NormName": null,
      "PublishNormCode": null,
      "ParentName": null
    },
    {
      "Item": "(Tăng)/giảm hàng tồn kho",
      "Values": {
        "KyNay": 12522684626,
        "KyTruoc": -14051247442,
        "LuyKe_KyNay": null,
        "LuyKe_KyTruoc": null
      },
      "ReportNormID": null,
      "Code": "10",
      "NormName": null,
      "PublishNormCode": null,
      "ParentName": null
    },
    {
      "Item": "Tăng/(giảm) các khoản phải trả (không kể lãi vay phải trả, thuế thu nhập doanh nghiệp phải nộp)",
      "Values": {
        "KyNay": -22038188028,
        "KyTruoc": -24780349337,
        "LuyKe_KyNay": null,
        "LuyKe_KyTruoc": null
      },
      "ReportNormID": null,
      "Code": "11",
      "NormName": null,
      "PublishNormCode": null,
      "ParentName": null
    },
    {
      "Item": "(Tăng)/giảm chi phí trả trước",
      "Values": {
        "KyNay": -53670818331,
        "KyTruoc": 4512641769,
        "LuyKe_KyNay": null,
        "LuyKe_KyTruoc": null
      },
      "ReportNormID": null,
      "Code": "12",
      "NormName": null,
      "PublishNormCode": null,
      "ParentName": null
    },
    {
      "Item": "Tăng/giảm chứng khoán kinh doanh",
      "Values": {
        "KyNay": null,
        "KyTruoc": null,
        "LuyKe_KyNay": null,
        "LuyKe_KyTruoc": null
      },
      "ReportNormID": null,
      "Code": "13",
      "NormName": null,
      "PublishNormCode": null,
      "ParentName": null
    },
    {
      "Item": "Tiền lãi vay đã trả",
      "Values": {
        "KyNay": -19639241376,
        "KyTruoc": -23346940499,
        "LuyKe_KyNay": null,
        "LuyKe_KyTruoc": null
      },
      "ReportNormID": null,
      "Code": "14",
      "NormName": null,
      "PublishNormCode": null,
      "ParentName": null
    },
    {
      "Item": "Thuế thu nhập doanh nghiệp đã nộp",
      "Values": {
        "KyNay": -787430290,
        "KyTruoc": -2135614902,
        "LuyKe_KyNay": null,
        "LuyKe_KyTruoc": null
      },
      "ReportNormID": null,
      "Code": "15",
      "NormName": null,
      "PublishNormCode": null,
      "ParentName": null
    },
    {
      "Item": "Tiền thu khác từ hoạt động kinh doanh",
      "Values": {
        "KyNay": 25581270000,
        "KyTruoc": null,
        "LuyKe_KyNay": null,
        "LuyKe_KyTruoc": null
      },
      "ReportNormID": null,
      "Code": "16",
      "NormName": null,
      "PublishNormCode": null,
      "ParentName": null
    },
    {
      "Item": "Các điều chỉnh khác",
      "Values": {
        "KyNay": -293336588327,
        "KyTruoc": null,
        "LuyKe_KyNay": null,
        "LuyKe_KyTruoc": null
      },
      "ReportNormID": null,
      "Code": null,
      "NormName": null,
      "PublishNormCode": null,
      "ParentName": null
    },
    {
      "Item": "Lưu chuyển tiền thuần từ hoạt động kinh doanh",
      "Values": {
        "KyNay": -67642708207,
        "KyTruoc": 40913107833,
        "LuyKe_KyNay": null,
        "LuyKe_KyTruoc": null
      },
      "ReportNormID": null,
      "Code": "20",
      "NormName": null,
      "PublishNormCode": null,
      "ParentName": null
    },
    {
      "Item": "Lưu chuyển tiền từ hoạt động đầu tư",
      "Values": {
        "KyNay": null,
        "KyTruoc": null,
        "LuyKe_KyNay": null,
        "LuyKe_KyTruoc": null
      },
      "ReportNormID": null,
      "Code": null,
      "NormName": null,
      "PublishNormCode": null,
      "ParentName": null
    },
    {
      "Item": "Tiền chi để mua sắm, xây dựng TSCĐ và các tài sản dài hạn khác",
      "Values": {
        "KyNay": -27387912903,
        "KyTruoc": -6257540782,
        "LuyKe_KyNay": null,
        "LuyKe_KyTruoc": null
      },
      "ReportNormID": null,
      "Code": "21",
      "NormName": null,
      "PublishNormCode": null,
      "ParentName": "Lưu chuyển tiền từ hoạt động đầu tư"
    },
    {
      "Item": "Tiền thu thanh lý, nhượng bán TSCĐ và các tài sản dài hạn khác",
      "Values": {
        "KyNay": 6257540782,
        "KyTruoc": null,
        "LuyKe_KyNay": null,
        "LuyKe_KyTruoc": null
      },
      "ReportNormID": null,
      "Code": "22",
      "NormName": null,
      "PublishNormCode": null,
      "ParentName": "Lưu chuyển tiền từ hoạt động đầu tư"
    },
    {
      "Item": "Tiền chi cho vay, mua các công cụ nợ của đơn vị khác",
      "Values": {
        "KyNay": -26588010013,
        "KyTruoc": -39000000000,
        "LuyKe_KyNay": null,
        "LuyKe_KyTruoc": null
      },
      "ReportNormID": null,
      "Code": "23",
      "NormName": null,
      "PublishNormCode": null,
      "ParentName": "Lưu chuyển tiền từ hoạt động đầu tư"
    },
    {
      "Item": "Tiền thu hồi cho vay, bán lại các công cụ nợ của đơn vị khác",
      "Values": {
        "KyNay": 20000000000,
        "KyTruoc": 1000000000,
        "LuyKe_KyNay": null,
        "LuyKe_KyTruoc": null
      },
      "ReportNormID": null,
      "Code": "24",
      "NormName": null,
      "PublishNormCode": null,
      "ParentName": "Lưu chuyển tiền từ hoạt động đầu tư"
    },
    {
      "Item": "Tiền thu hồi đầu tư góp vốn vào đơn vị khác",
      "Values": {
        "KyNay": 67322000000,
        "KyTruoc": null,
        "LuyKe_KyNay": null,
        "LuyKe_KyTruoc": null
      },
      "ReportNormID": null,
      "Code": "26",
      "NormName": null,
      "PublishNormCode": null,
      "ParentName": "Lưu chuyển tiền từ hoạt động đầu tư"
    },
    {
      "Item": "Tiền thu lãi vay, cổ tức và lợi nhuận được chia",
      "Values": {
        "KyNay": 1375541269,
        "KyTruoc": 2301823358,
        "LuyKe_KyNay": null,
        "LuyKe_KyTruoc": null
      },
      "ReportNormID": null,
      "Code": "27",
      "NormName": null,
      "PublishNormCode": null,
      "ParentName": "Lưu chuyển tiền từ hoạt động đầu tư"
    },
    {
      "Item": "Lưu chuyển tiền thuần từ hoạt động đầu tư",
      "Values": {
        "KyNay": 34721618353,
        "KyTruoc": -35698176642,
        "LuyKe_KyNay": null,
        "LuyKe_KyTruoc": null
      },
      "ReportNormID": null,
      "Code": "30",
      "NormName": null,
      "PublishNormCode": null,
      "ParentName": null
    },
    {
      "Item": "Lưu chuyển tiền từ hoạt động tài chính",
      "Values": {
        "KyNay": null,
        "KyTruoc": null,
        "LuyKe_KyNay": null,
        "LuyKe_KyTruoc": null
      },
      "ReportNormID": null,
      "Code": null,
      "NormName": null,
      "PublishNormCode": null,
      "ParentName": null
    },
    {
      "Item": "Tiền thu từ đi vay",
      "Values": {
        "KyNay": 283321538050,
        "KyTruoc": 241828429841,
        "LuyKe_KyNay": null,
        "LuyKe_KyTruoc": null
      },
      "ReportNormID": null,
      "Code": "33",
      "NormName": null,
      "PublishNormCode": null,
      "ParentName": "Lưu chuyển tiền từ hoạt động tài chính"
    },
    {
      "Item": "Tiền trả nợ gốc vay",
      "Values": {
        "KyNay": -239779712908,
        "KyTruoc": -258355837948,
        "LuyKe_KyNay": null,
        "LuyKe_KyTruoc": null
      },
      "ReportNormID": null,
      "Code": "34",
      "NormName": null,
      "PublishNormCode": null,
      "ParentName": "Lưu chuyển tiền từ hoạt động tài chính"
    },
    {
      "Item": "Tiền chi trả nợ gốc thuê tài chính",
      "Values": {
        "KyNay": -1192843714,
        "KyTruoc": -2424797060,
        "LuyKe_KyNay": null,
        "LuyKe_KyTruoc": null
      },
      "ReportNormID": null,
      "Code": "35",
      "NormName": null,
      "PublishNormCode": null,
      "ParentName": "Lưu chuyển tiền từ hoạt động tài chính"
    },
    {
      "Item": "Lưu chuyển tiền thuần từ hoạt động tài chính",
      "Values": {
        "KyNay": 42348981428,
        "KyTruoc": -18952205167,
        "LuyKe_KyNay": null,
        "LuyKe_KyTruoc": null
      },
      "ReportNormID": null,
      "Code": "40",
      "NormName": null,
      "PublishNormCode": null,
      "ParentName": null
    },
    {
      "Item": "Lưu chuyển tiền thuần trong năm",
      "Values": {
        "KyNay": 9427891574,
        "KyTruoc": -13737273976,
        "LuyKe_KyNay": null,
        "LuyKe_KyTruoc": null
      },
      "ReportNormID": null,
      "Code": "50",
      "NormName": null,
      "PublishNormCode": null,
      "ParentName": null
    },
    {
      "Item": "Tiền và tương đương tiền đầu năm",
      "Values": {
        "KyNay": 2079219084,
        "KyTruoc": 15812579609,
        "LuyKe_KyNay": null,
        "LuyKe_KyTruoc": null
      },
      "ReportNormID": null,
      "Code": "60",
      "NormName": null,
      "PublishNormCode": null,
      "ParentName": null
    },
    {
      "Item": "Ảnh hưởng của thay đổi tỷ giá hối đoái quy đổi ngoại tệ",
      "Values": {
        "KyNay": 3319462,
        "KyTruoc": 3913451,
        "LuyKe_KyNay": null,
        "LuyKe_KyTruoc": null
      },
      "ReportNormID": null,
      "Code": "61",
      "NormName": null,
      "PublishNormCode": null,
      "ParentName": null
    },
    {
      "Item": "Tiền và tương đương tiền cuối năm",
      "Values": {
        "KyNay": 11510430120,
        "KyTruoc": 2079219084,
        "LuyKe_KyNay": null,
        "LuyKe_KyTruoc": null
      },
      "ReportNormID": null,
      "Code": "70",
      "NormName": null,
      "PublishNormCode": null,
      "ParentName": null
    }
  ],
  "OffBalanceSheet": [],
  "CashFlowMethod": "Indirect",
  "Meta": {
    "MaCongTy": "AAT",
    "TenCongTy": "CTCP Tập Đoàn Tiên Sơn Thanh Hóa ",
    "KyBaoCao": "N",
    "Nam": 2024,
    "TrangThaiKiemDuyet": "KT",
    "TinhChatBaoCao": "HN",
    "ThuocTinhKhac": "CDC",
    "LoaiBaoCao": null,
    "NgayCongBoBCTC": "01/04/2025",
    "Url": "https://static2.vietstock.vn/data/HOSE/2024/BCTC/VN/NAM/AAT_Baocaotaichinh_2024_Kiemtoan_Hopnhat.pdf"
  },
  "MetaDB": {
    "AuditedNote": "Báo cáo tài chính hợp nhất kèm theo được kiểm toán bởi Công ty TNHH Kiểm toán và Tư vấn UHY.",
    "Note": null,
    "CtyKiemToan": "CÔNG TY TNHH KIỂM TOÁN VÀ TƯ VẤN UHY",
    "NgayKiemToan": "2025-03-29"
  }
}